pompy_cli/CLIContext.py
pompy_cli/Header.py
pompy_cli/__init__.py
pompy_cli/demo_basic.py
pompy_cli/demo_context.py
pompy_cli/prompt.py
pompy_cli/style.py
pompy_cli/util.py
pompy_cli-0.2.0.dist-info/licenses/LICENSE
pompy_cli-0.2.0.dist-info/METADATA
pompy_cli-0.2.0.dist-info/WHEEL
pompy_cli-0.2.0.dist-info/top_level.txt
pompy_cli-0.2.0.dist-info/RECORD
